{
  "file_path": "organized_dataset_All\\147_edit.php",
  "rector_analysis": {
    "php_version_changes": 4,
    "rules_triggered": [
      "Rector\\Php53\\Rector\\FuncCall\\DirNameFileConstantToDirConstantRector",
      "Rector\\Php54\\Rector\\Array_\\LongArrayToShortArrayRector",
      "Rector\\Php80\\Rector\\NotIdentical\\StrContainsRector",
      "Rector\\Php81\\Rector\\FuncCall\\NullToStrictStringFuncCallArgRector"
    ],
    "changes_by_php_version": {
      "php_53": 1,
      "php_54": 1,
      "php_80": 1,
      "php_81": 1
    },
    "has_diff": true,
    "diff_line_count": 210
  },
  "analysis_metadata": {
    "rector_version": "2.1.0",
    "analysis_date": "2025-11-13T04:07:43.648259",
    "file_size_kb": 14.1,
    "analysis_type": "version_specific_only"
  },
  "raw_rector_output": {
    "totals": {
      "changed_files": 1,
      "errors": 0
    },
    "file_diffs": [
      {
        "file": "dataset/organized_dataset_All/147_edit.php",
        "diff": "--- Original\n+++ New\n@@ -7,7 +7,7 @@\n  */\n \n /** WordPress Administration Bootstrap */\n-require_once( dirname( __FILE__ ) . '/admin.php' );\n+require_once( __DIR__ . '/admin.php' );\n \n if ( ! $typenow )\n \twp_die( __( 'Invalid post type' ) );\n@@ -31,7 +31,7 @@\n $pagenum = $wp_list_table->get_pagenum();\n \n // Back-compat for viewing comments of an entry\n-foreach ( array( 'p', 'attachment_id', 'page_id' ) as $_redirect ) {\n+foreach ( [ 'p', 'attachment_id', 'page_id' ] as $_redirect ) {\n \tif ( ! empty( $_REQUEST[ $_redirect ] ) ) {\n \t\twp_redirect( admin_url( 'edit-comments.php?p=' . absint( $_REQUEST[ $_redirect ] ) ) );\n \t\texit;\n@@ -54,15 +54,15 @@\n if ( $doaction ) {\n \tcheck_admin_referer('bulk-posts');\n \n-\t$sendback = remove_query_arg( array('trashed', 'untrashed', 'deleted', 'locked', 'ids'), wp_get_referer() );\n+\t$sendback = remove_query_arg( ['trashed', 'untrashed', 'deleted', 'locked', 'ids'], wp_get_referer() );\n \tif ( ! $sendback )\n \t\t$sendback = admin_url( $parent_file );\n \t$sendback = add_query_arg( 'paged', $pagenum, $sendback );\n-\tif ( strpos($sendback, 'post.php') !== false )\n+\tif ( str_contains($sendback, 'post.php') )\n \t\t$sendback = admin_url($post_new_file);\n \n \tif ( 'delete_all' == $doaction ) {\n-\t\t$post_status = preg_replace('/[^a-z0-9_-]+/i', '', $_REQUEST['post_status']);\n+\t\t$post_status = preg_replace('/[^a-z0-9_-]+/i', '', (string) $_REQUEST['post_status']);\n \t\tif ( get_post_status_object($post_status) ) // Check the post status exists first\n \t\t\t$post_ids = $wpdb->get_col( $wpdb->prepare( \"SELECT ID FROM $wpdb->posts WHERE post_type=%s AND post_status = %s\", $post_type, $post_status ) );\n \t\t$doaction = 'delete';\n@@ -69,7 +69,7 @@\n \t} elseif ( isset( $_REQUEST['media'] ) ) {\n \t\t$post_ids = $_REQUEST['media'];\n \t} elseif ( isset( $_REQUEST['ids'] ) ) {\n-\t\t$post_ids = explode( ',', $_REQUEST['ids'] );\n+\t\t$post_ids = explode( ',', (string) $_REQUEST['ids'] );\n \t} elseif ( !empty( $_REQUEST['post'] ) ) {\n \t\t$post_ids = array_map('intval', $_REQUEST['post']);\n \t}\n@@ -98,7 +98,7 @@\n \t\t\t\t$trashed++;\n \t\t\t}\n \n-\t\t\t$sendback = add_query_arg( array('trashed' => $trashed, 'ids' => join(',', $post_ids), 'locked' => $locked ), $sendback );\n+\t\t\t$sendback = add_query_arg( ['trashed' => $trashed, 'ids' => join(',', $post_ids), 'locked' => $locked ], $sendback );\n \t\t\tbreak;\n \t\tcase 'untrash':\n \t\t\t$untrashed = 0;\n@@ -146,12 +146,12 @@\n \t\t\tbreak;\n \t}\n \n-\t$sendback = remove_query_arg( array('action', 'action2', 'tags_input', 'post_author', 'comment_status', 'ping_status', '_status', 'post', 'bulk_edit', 'post_view'), $sendback );\n+\t$sendback = remove_query_arg( ['action', 'action2', 'tags_input', 'post_author', 'comment_status', 'ping_status', '_status', 'post', 'bulk_edit', 'post_view'], $sendback );\n \n \twp_redirect($sendback);\n \texit();\n } elseif ( ! empty($_REQUEST['_wp_http_referer']) ) {\n-\t wp_redirect( remove_query_arg( array('_wp_http_referer', '_wpnonce'), wp_unslash($_SERVER['REQUEST_URI']) ) );\n+\t wp_redirect( remove_query_arg( ['_wp_http_referer', '_wpnonce'], wp_unslash($_SERVER['REQUEST_URI']) ) );\n \t exit;\n }\n \n@@ -162,13 +162,13 @@\n $title = $post_type_object->labels->name;\n \n if ( 'post' == $post_type ) {\n-\tget_current_screen()->add_help_tab( array(\n+\tget_current_screen()->add_help_tab( [\n \t'id'\t\t=> 'overview',\n \t'title'\t\t=> __('Overview'),\n \t'content'\t=>\n \t\t'<p>' . __('This screen provides access to all of your posts. You can customize the display of this screen to suit your workflow.') . '</p>'\n-\t) );\n-\tget_current_screen()->add_help_tab( array(\n+\t] );\n+\tget_current_screen()->add_help_tab( [\n \t'id'\t\t=> 'screen-content',\n \t'title'\t\t=> __('Screen Content'),\n \t'content'\t=>\n@@ -179,8 +179,8 @@\n \t\t\t'<li>' . __('You can view posts in a simple title list or with an excerpt. Choose the view you prefer by clicking on the icons at the top of the list on the right.') . '</li>' .\n \t\t\t'<li>' . __('You can refine the list to show only posts in a specific category or from a specific month by using the dropdown menus above the posts list. Click the Filter button after making your selection. You also can refine the list by clicking on the post author, category or tag in the posts list.') . '</li>' .\n \t\t'</ul>'\n-\t) );\n-\tget_current_screen()->add_help_tab( array(\n+\t] );\n+\tget_current_screen()->add_help_tab( [\n \t'id'\t\t=> 'action-links',\n \t'title'\t\t=> __('Available Actions'),\n \t'content'\t=>\n@@ -191,14 +191,14 @@\n \t\t\t'<li>' . __('<strong>Trash</strong> removes your post from this list and places it in the trash, from which you can permanently delete it.') . '</li>' .\n \t\t\t'<li>' . __('<strong>Preview</strong> will show you what your draft post will look like if you publish it. View will take you to your live site to view the post. Which link is available depends on your post&#8217;s status.') . '</li>' .\n \t\t'</ul>'\n-\t) );\n-\tget_current_screen()->add_help_tab( array(\n+\t] );\n+\tget_current_screen()->add_help_tab( [\n \t'id'\t\t=> 'bulk-actions',\n \t'title'\t\t=> __('Bulk Actions'),\n \t'content'\t=>\n \t\t'<p>' . __('You can also edit or move multiple posts to the trash at once. Select the posts you want to act on using the checkboxes, then select the action you want to take from the Bulk Actions menu and click Apply.') . '</p>' .\n \t\t\t\t'<p>' . __('When using Bulk Edit, you can change the metadata (categories, author, etc.) for all selected posts at once. To remove a post from the grouping, just click the x next to its name in the Bulk Edit area that appears.') . '</p>'\n-\t) );\n+\t] );\n \n \tget_current_screen()->set_help_sidebar(\n \t'<p><strong>' . __('For more information:') . '</strong></p>' .\n@@ -207,19 +207,19 @@\n \t);\n \n } elseif ( 'page' == $post_type ) {\n-\tget_current_screen()->add_help_tab( array(\n+\tget_current_screen()->add_help_tab( [\n \t'id'\t\t=> 'overview',\n \t'title'\t\t=> __('Overview'),\n \t'content'\t=>\n \t\t'<p>' . __('Pages are similar to posts in that they have a title, body text, and associated metadata, but they are different in that they are not part of the chronological blog stream, kind of like permanent posts. Pages are not categorized or tagged, but can have a hierarchy. You can nest pages under other pages by making one the &#8220;Parent&#8221; of the other, creating a group of pages.') . '</p>'\n-\t) );\n-\tget_current_screen()->add_help_tab( array(\n+\t] );\n+\tget_current_screen()->add_help_tab( [\n \t'id'\t\t=> 'managing-pages',\n \t'title'\t\t=> __('Managing Pages'),\n \t'content'\t=>\n \t\t'<p>' . __('Managing pages is very similar to managing posts, and the screens can be customized in the same way.') . '</p>' .\n \t\t'<p>' . __('You can also perform the same types of actions, including narrowing the list by using the filters, acting on a page using the action links that appear when you hover over a row, or using the Bulk Actions menu to edit the metadata for multiple pages at once.') . '</p>'\n-\t) );\n+\t] );\n \n \tget_current_screen()->set_help_sidebar(\n \t'<p><strong>' . __('For more information:') . '</strong></p>' .\n@@ -228,31 +228,31 @@\n \t);\n }\n \n-add_screen_option( 'per_page', array( 'label' => $title, 'default' => 20, 'option' => 'edit_' . $post_type . '_per_page' ) );\n+add_screen_option( 'per_page', [ 'label' => $title, 'default' => 20, 'option' => 'edit_' . $post_type . '_per_page' ] );\n \n-$bulk_counts = array(\n+$bulk_counts = [\n \t'updated'   => isset( $_REQUEST['updated'] )   ? absint( $_REQUEST['updated'] )   : 0,\n \t'locked'    => isset( $_REQUEST['locked'] )    ? absint( $_REQUEST['locked'] )    : 0,\n \t'deleted'   => isset( $_REQUEST['deleted'] )   ? absint( $_REQUEST['deleted'] )   : 0,\n \t'trashed'   => isset( $_REQUEST['trashed'] )   ? absint( $_REQUEST['trashed'] )   : 0,\n \t'untrashed' => isset( $_REQUEST['untrashed'] ) ? absint( $_REQUEST['untrashed'] ) : 0,\n-);\n+];\n \n-$bulk_messages = array();\n-$bulk_messages['post'] = array(\n+$bulk_messages = [];\n+$bulk_messages['post'] = [\n \t'updated'   => _n( '%s post updated.', '%s posts updated.', $bulk_counts['updated'] ),\n \t'locked'    => _n( '%s post not updated, somebody is editing it.', '%s posts not updated, somebody is editing them.', $bulk_counts['locked'] ),\n \t'deleted'   => _n( '%s post permanently deleted.', '%s posts permanently deleted.', $bulk_counts['deleted'] ),\n \t'trashed'   => _n( '%s post moved to the Trash.', '%s posts moved to the Trash.', $bulk_counts['trashed'] ),\n \t'untrashed' => _n( '%s post restored from the Trash.', '%s posts restored from the Trash.', $bulk_counts['untrashed'] ),\n-);\n-$bulk_messages['page'] = array(\n+];\n+$bulk_messages['page'] = [\n \t'updated'   => _n( '%s page updated.', '%s pages updated.', $bulk_counts['updated'] ),\n \t'locked'    => _n( '%s page not updated, somebody is editing it.', '%s pages not updated, somebody is editing them.', $bulk_counts['locked'] ),\n \t'deleted'   => _n( '%s page permanently deleted.', '%s pages permanently deleted.', $bulk_counts['deleted'] ),\n \t'trashed'   => _n( '%s page moved to the Trash.', '%s pages moved to the Trash.', $bulk_counts['trashed'] ),\n \t'untrashed' => _n( '%s page restored from the Trash.', '%s pages restored from the Trash.', $bulk_counts['untrashed'] ),\n-);\n+];\n \n /**\n  * Filter the bulk action updated messages.\n@@ -281,7 +281,7 @@\n \n <?php\n // If we have a bulk message to issue:\n-$messages = array();\n+$messages = [];\n foreach ( $bulk_counts as $message => $count ) {\n \tif ( isset( $bulk_messages[ $post_type ][ $message ] ) )\n \t\t$messages[] = sprintf( $bulk_messages[ $post_type ][ $message ], number_format_i18n( $count ) );\n@@ -289,7 +289,7 @@\n \t\t$messages[] = sprintf( $bulk_messages['post'][ $message ], number_format_i18n( $count ) );\n \n \tif ( $message == 'trashed' && isset( $_REQUEST['ids'] ) ) {\n-\t\t$ids = preg_replace( '/[^0-9,]/', '', $_REQUEST['ids'] );\n+\t\t$ids = preg_replace( '/[^0-9,]/', '', (string) $_REQUEST['ids'] );\n \t\t$messages[] = '<a href=\"' . esc_url( wp_nonce_url( \"edit.php?post_type=$post_type&doaction=undo&action=untrash&ids=$ids\", \"bulk-posts\" ) ) . '\">' . __('Undo') . '</a>';\n \t}\n }\n@@ -298,7 +298,7 @@\n \techo '<div id=\"message\" class=\"updated\"><p>' . join( ' ', $messages ) . '</p></div>';\n unset( $messages );\n \n-$_SERVER['REQUEST_URI'] = remove_query_arg( array( 'locked', 'skipped', 'updated', 'deleted', 'trashed', 'untrashed' ), $_SERVER['REQUEST_URI'] );\n+$_SERVER['REQUEST_URI'] = remove_query_arg( [ 'locked', 'skipped', 'updated', 'deleted', 'trashed', 'untrashed' ], $_SERVER['REQUEST_URI'] );\n ?>\n \n <?php $wp_list_table->views(); ?>\n",
        "applied_rectors": [
          "Rector\\Php53\\Rector\\FuncCall\\DirNameFileConstantToDirConstantRector",
          "Rector\\Php54\\Rector\\Array_\\LongArrayToShortArrayRector",
          "Rector\\Php80\\Rector\\NotIdentical\\StrContainsRector",
          "Rector\\Php81\\Rector\\FuncCall\\NullToStrictStringFuncCallArgRector"
        ]
      }
    ],
    "changed_files": [
      "dataset/organized_dataset_All/147_edit.php"
    ]
  }
}