{
  "file_path": "organized_dataset_All\\251_template-tags.php",
  "rector_analysis": {
    "php_version_changes": 1,
    "rules_triggered": [
      "Rector\\Php54\\Rector\\Array_\\LongArrayToShortArrayRector"
    ],
    "changes_by_php_version": {
      "php_54": 1
    },
    "has_diff": true,
    "diff_line_count": 42
  },
  "analysis_metadata": {
    "rector_version": "2.1.0",
    "analysis_date": "2025-11-13T04:12:16.338438",
    "file_size_kb": 6.0,
    "analysis_type": "version_specific_only"
  },
  "raw_rector_output": {
    "totals": {
      "changed_files": 1,
      "errors": 0
    },
    "file_diffs": [
      {
        "file": "dataset/organized_dataset_All/251_template-tags.php",
        "diff": "--- Original\n+++ New\n@@ -26,7 +26,7 @@\n \n \t$paged        = get_query_var( 'paged' ) ? intval( get_query_var( 'paged' ) ) : 1;\n \t$pagenum_link = html_entity_decode( get_pagenum_link() );\n-\t$query_args   = array();\n+\t$query_args   = [];\n \t$url_parts    = explode( '?', $pagenum_link );\n \n \tif ( isset( $url_parts[1] ) ) {\n@@ -40,7 +40,7 @@\n \t$format .= $wp_rewrite->using_permalinks() ? user_trailingslashit( $wp_rewrite->pagination_base . '/%#%', 'paged' ) : '?paged=%#%';\n \n \t// Set up paginated links.\n-\t$links = paginate_links( array(\n+\t$links = paginate_links( [\n \t\t'base'     => $pagenum_link,\n \t\t'format'   => $format,\n \t\t'total'    => $wp_query->max_num_pages,\n@@ -49,7 +49,7 @@\n \t\t'add_args' => array_map( 'urlencode', $query_args ),\n \t\t'prev_text' => __( '&larr; Previous', 'twentyfourteen' ),\n \t\t'next_text' => __( 'Next &rarr;', 'twentyfourteen' ),\n-\t) );\n+\t] );\n \n \tif ( $links ) :\n \n@@ -130,9 +130,9 @@\n function twentyfourteen_categorized_blog() {\n \tif ( false === ( $all_the_cool_cats = get_transient( 'twentyfourteen_category_count' ) ) ) {\n \t\t// Create an array of all the categories that are attached to posts\n-\t\t$all_the_cool_cats = get_categories( array(\n+\t\t$all_the_cool_cats = get_categories( [\n \t\t\t'hide_empty' => 1,\n-\t\t) );\n+\t\t] );\n \n \t\t// Count the number of categories that are attached to the posts\n \t\t$all_the_cool_cats = count( $all_the_cool_cats );\n",
        "applied_rectors": [
          "Rector\\Php54\\Rector\\Array_\\LongArrayToShortArrayRector"
        ]
      }
    ],
    "changed_files": [
      "dataset/organized_dataset_All/251_template-tags.php"
    ]
  }
}